lazystats/Randnums.py
lazystats/__init__.py
lazystats-0.0.3.dist-info/LICENSE
lazystats-0.0.3.dist-info/METADATA
lazystats-0.0.3.dist-info/WHEEL
lazystats-0.0.3.dist-info/top_level.txt
lazystats-0.0.3.dist-info/RECORD
